{
    "title": "Что нового?",
    "description": "1. Исправлены проблемы с выключением бота из-за каких-то незначительных ошибок. Теперь все ошибки сохраняются в базе, а бот не \"падает\".\n2. Временно убраны музыкальные команды до момента исправления алгоритма их работы. \n3. Исправлена проблема с неккоректным отображением времени и даты. Проблема была в том, что при запуске приложения время и дата записывались в переменную один раз и больше не обновлялись.\n4. Убрана команда `invite`, так как может быть использована для спама/флуда с целью рекламы серверов.",
    "color": 5814783,
    "footer": {
      "text": "Обновление 1.0.9"
    }
  }